{
    "categoryCount": 10,
    "failure": {
        "failure_0": {
            "actual": 0,
            "output": [
                6.404684543609619,
                -10.649591445922852,
                2.441074848175049,
                -3.7519099712371826,
                2.2892777919769287,
                4.745920658111572,
                9.935819625854492,
                0.661633312702179,
                -7.2143940925598145,
                -1.2892314195632935
            ],
            "predicted": 6
        },
        "failure_1": {
            "actual": 1,
            "output": [
                -5.615696430206299,
                7.323880672454834,
                -2.0505878925323486,
                2.8066399097442627,
                0.2726002633571625,
                -1.7234388589859009,
                -3.2613399028778076,
                0.8822903037071228,
                8.204826354980469,
                -8.518556594848633
            ],
            "predicted": 8
        },
        "failure_2": {
            "actual": 2,
            "output": [
                -0.2786732316017151,
                0.8910790085792542,
                5.8214006423950195,
                3.753314256668091,
                -7.714102268218994,
                -6.182325839996338,
                -8.852147102355957,
                7.346149921417236,
                3.478074550628662,
                1.2652661800384521
            ],
            "predicted": 7
        },
        "failure_3": {
            "actual": 3,
            "output": [
                -2.1374802589416504,
                -7.726102352142334,
                -2.927354574203491,
                3.9006872177124023,
                -3.5128183364868164,
                2.1593823432922363,
                -1.60841965675354,
                -10.11453628540039,
                8.656485557556152,
                3.652089834213257
            ],
            "predicted": 8
        },
        "failure_4": {
            "actual": 4,
            "output": [
                -2.1154468059539795,
                0.9773721098899841,
                10.779626846313477,
                -1.704451560974121,
                3.4363811016082764,
                -3.994154453277588,
                6.016993999481201,
                -6.003614902496338,
                1.783919334411621,
                -5.076051712036133
            ],
            "predicted": 2
        },
        "failure_5": {
            "actual": 5,
            "output": [
                -3.2604448795318604,
                2.3107705116271973,
                -3.0795905590057373,
                7.671905994415283,
                -5.025547981262207,
                4.305856227874756,
                -0.9740705490112305,
                -3.3483235836029053,
                -2.618396282196045,
                -1.632886290550232
            ],
            "predicted": 3
        },
        "failure_6": {
            "actual": 6,
            "output": [
                9.36108684539795,
                -8.106640815734863,
                0.797294557094574,
                -2.9589502811431885,
                0.8108134865760803,
                2.1328952312469482,
                9.0272798538208,
                -1.7746591567993164,
                -0.8565332889556885,
                -3.693575859069824
            ],
            "predicted": 0
        },
        "failure_7": {
            "actual": 7,
            "output": [
                -7.072797775268555,
                2.3383629322052,
                0.6156030297279358,
                3.190438747406006,
                7.253265857696533,
                -8.899904251098633,
                -10.323295593261719,
                6.513745307922363,
                -0.29131317138671875,
                4.183352947235107
            ],
            "predicted": 4
        },
        "failure_8": {
            "actual": 8,
            "output": [
                3.2425620555877686,
                -5.905026435852051,
                11.05311107635498,
                2.2715976238250732,
                -2.719144344329834,
                -4.081152439117432,
                0.7972412109375,
                -6.143848419189453,
                5.158475875854492,
                -0.454113245010376
            ],
            "predicted": 2
        },
        "failure_9": {
            "actual": 9,
            "output": [
                -3.6953349113464355,
                -11.55447769165039,
                -1.496656894683838,
                1.4025683403015137,
                -3.075016975402832,
                5.04926061630249,
                -6.3230743408203125,
                -8.910496711730957,
                8.231880187988281,
                8.128093719482422
            ],
            "predicted": 8
        }
    },
    "layers": [
        {
            "channels": 1,
            "height": 32,
            "name": "input",
            "type": "Input2D",
            "width": 32
        },
        {
            "height": 32,
            "name": "c1",
            "nodeCount": 6,
            "size": 5,
            "type": "Convolutional",
            "width": 32
        },
        {
            "height": 28,
            "name": "s2",
            "nodeCount": 6,
            "size": 2,
            "stride": 2,
            "transition": "Sigmoid",
            "type": "Convolutional",
            "width": 28
        },
        {
            "height": 14,
            "name": "c3",
            "nodeCount": 6,
            "size": 5,
            "type": "Convolutional",
            "width": 14
        },
        {
            "height": 10,
            "name": "s4",
            "nodeCount": 6,
            "size": 2,
            "stride": 2,
            "transition": "Sigmoid",
            "type": "Convolutional",
            "width": 10
        },
        {
            "name": "fc5",
            "nodeCount": 120,
            "type": "FullyConnected"
        },
        {
            "name": "fc6",
            "nodeCount": 84,
            "transition": "Sigmoid",
            "type": "FullyConnected"
        },
        {
            "name": "fc7",
            "nodeCount": 10,
            "type": "FullyConnected"
        }
    ],
    "success": {
        "success_0": {
            "actual": 0,
            "output": [
                14.260648727416992,
                -5.167076110839844,
                -2.1836462020874023,
                -1.0225392580032349,
                -7.448437213897705,
                3.295731782913208,
                2.2753210067749023,
                -0.35016557574272156,
                -1.2759149074554443,
                -0.8092426061630249
            ],
            "predicted": 0
        },
        "success_1": {
            "actual": 1,
            "output": [
                -4.790286540985107,
                16.175268173217773,
                -1.1545263528823853,
                -3.1856935024261475,
                1.045387864112854,
                -6.057112693786621,
                -0.6577587127685547,
                0.9257263541221619,
                5.042123794555664,
                -6.673722743988037
            ],
            "predicted": 1
        },
        "success_2": {
            "actual": 2,
            "output": [
                -1.865750789642334,
                5.393589019775391,
                14.344891548156738,
                2.3690268993377686,
                -3.050238847732544,
                -4.241462707519531,
                -2.4290173053741455,
                -3.328383684158325,
                0.594218373298645,
                -6.483860015869141
            ],
            "predicted": 2
        },
        "success_3": {
            "actual": 3,
            "output": [
                -3.1746058464050293,
                -4.133063793182373,
                -4.008765697479248,
                15.723923683166504,
                -4.4792327880859375,
                3.54512095451355,
                -12.566092491149902,
                -0.2954961359500885,
                -2.586514949798584,
                4.669741630554199
            ],
            "predicted": 3
        },
        "success_4": {
            "actual": 4,
            "output": [
                -7.239459991455078,
                -9.037548065185547,
                -2.6483700275421143,
                -3.9685049057006836,
                15.30844783782959,
                -2.961615800857544,
                -0.23846399784088135,
                0.07167139649391174,
                -1.7928729057312012,
                7.599354267120361
            ],
            "predicted": 4
        },
        "success_5": {
            "actual": 5,
            "output": [
                -5.514235973358154,
                -6.527070999145508,
                -6.831742286682129,
                -2.7651402950286865,
                -1.7710906267166138,
                8.412311553955078,
                5.940059185028076,
                -0.7184426784515381,
                2.931138515472412,
                1.6241289377212524
            ],
            "predicted": 5
        },
        "success_6": {
            "actual": 6,
            "output": [
                4.725358486175537,
                -5.021368503570557,
                0.647291362285614,
                -4.6003265380859375,
                -6.824595928192139,
                3.193882942199707,
                16.937015533447266,
                -5.420821666717529,
                4.475175857543945,
                -6.362782001495361
            ],
            "predicted": 6
        },
        "success_7": {
            "actual": 7,
            "output": [
                0.4981064796447754,
                -2.0188064575195312,
                0.5399795174598694,
                -0.5692026019096375,
                -3.414518117904663,
                -0.13448959589004517,
                -9.50287914276123,
                18.464242935180664,
                -4.185886859893799,
                1.8712643384933472
            ],
            "predicted": 7
        },
        "success_8": {
            "actual": 8,
            "output": [
                -3.6952013969421387,
                -7.298937797546387,
                2.731646776199341,
                -0.19747468829154968,
                -5.588362216949463,
                3.186338186264038,
                -3.9392688274383545,
                -5.603287220001221,
                12.214987754821777,
                1.14165198802948
            ],
            "predicted": 8
        },
        "success_9": {
            "actual": 9,
            "output": [
                -11.475969314575195,
                -3.6166157722473145,
                -1.1637742519378662,
                1.1187012195587158,
                2.985778331756592,
                1.1079127788543701,
                -5.301851272583008,
                -0.7847135663032532,
                -2.9456450939178467,
                14.692718505859375
            ],
            "predicted": 9
        }
    }
}